BiofilmSimulation/__init__.py
BiofilmSimulation/bacteria.py
BiofilmSimulation/biofilm.py
BiofilmSimulation/constants.py
BiofilmSimulation/data_handling.py
BiofilmSimulation/formulas.py
BiofilmSimulation/plotting.py
BiofilmSimulation/utils.py
BiofilmSimulation-1.0.3.dist-info/LICENSE
BiofilmSimulation-1.0.3.dist-info/METADATA
BiofilmSimulation-1.0.3.dist-info/WHEEL
BiofilmSimulation-1.0.3.dist-info/top_level.txt
BiofilmSimulation-1.0.3.dist-info/RECORD
