Metadata-Version: 2.1
Name: BiofilmSimulation
Version: 1.0.3
Summary: The model applies methods from molecular dynamics (MD) and takes into account different physical and biological effects. The software provides great flexibility by enabling the user to switch easily between sets of constants e.g. to model different bacterial strains. Furthermore, the software includes functions for visualisation of the models behaviour over time.
Home-page: https://github.com/StudDavid/biofilm_growth_modeling
Author: David Theidel, Thorben Klamt, Tizian Dege, Jonas Müller
Author-email: theidel@stud.uni-hannover.de
License: MIT License
Platform: UNKNOWN
Classifier: Programming Language :: Python :: 3
Classifier: License :: OSI Approved :: MIT License
Classifier: Operating System :: OS Independent
Requires-Python: >=3.7
